TAInstCalorimetry/__init__.py
TAInstCalorimetry/DATA/1stgen.csv
TAInstCalorimetry/DATA/c3a.csv
TAInstCalorimetry/DATA/calorimetry_data_1.csv
TAInstCalorimetry/DATA/calorimetry_data_2.csv
TAInstCalorimetry/DATA/calorimetry_data_3.csv
TAInstCalorimetry/DATA/calorimetry_data_4.csv
TAInstCalorimetry/DATA/calorimetry_data_5.csv
TAInstCalorimetry/DATA/MOD_myexp1.csv
TAInstCalorimetry/DATA/MOD_OPC_1.xls
TAInstCalorimetry/DATA/myexp1.csv
TAInstCalorimetry/DATA/myexp2.csv
TAInstCalorimetry/DATA/myexp3.csv
TAInstCalorimetry/DATA/myexp4.csv
TAInstCalorimetry/DATA/myexp5.csv
TAInstCalorimetry/DATA/myexp6.csv
TAInstCalorimetry/DATA/myexp7.csv
TAInstCalorimetry/DATA/myexp8.csv
TAInstCalorimetry/DATA/OPC_1.xls
TAInstCalorimetry/DATA/OPC_2.xls
TAInstCalorimetry/DATA/opc_3.csv
TAInstCalorimetry/DATA/TEST_CALO_Gen1+2.csv
TAInstCalorimetry/DATA/TEST_CALO_Gen3.csv
TAInstCalorimetry/tacalorimetry.py
TAInstCalorimetry/utils.py
tainstcalorimetry-0.1.16.dist-info/LICENSE
tainstcalorimetry-0.1.16.dist-info/METADATA
tainstcalorimetry-0.1.16.dist-info/WHEEL
tainstcalorimetry-0.1.16.dist-info/RECORD
