Metadata-Version: 2.1
Name: tainstcalorimetry
Version: 0.1.16
Summary: Handling TAM Air calorimetry files made easy.
Home-page: https://github.com/mj-hofmann/TAInstCalorimetry
License: GNU GENERAL PUBLIC LICENSE
Keywords: calorimetry,TAM Air,TA Instruments,analysis,vizualisation
Author: mj-hofmann
Author-email: aCodingChemist@gmail.com
Requires-Python: >=3.8.1,<3.12
Classifier: License :: Other/Proprietary License
Classifier: Programming Language :: Python :: 3
Classifier: Programming Language :: Python :: 3.9
Classifier: Programming Language :: Python :: 3.10
Classifier: Programming Language :: Python :: 3.11
Requires-Dist: matplotlib (>=3.6.3,<4.0.0)
Requires-Dist: mypy (>=0.991,<0.992)
Requires-Dist: pandas (>=1.5.3,<2.0.0)
Requires-Dist: pysnooper (>=1.1.1,<2.0.0)
Requires-Dist: pytest (>=7.2.0,<8.0.0)
Requires-Dist: pytest-cov (>=4.0.0,<5.0.0)
Requires-Dist: requests (>=2.28.1,<3.0.0)
Requires-Dist: scipy (>=1.10.0,<2.0.0)
Requires-Dist: xlrd (>=2.0.1,<3.0.0)
Project-URL: Documentation, https://mj-hofmann.github.io/TAInstCalorimetry/
Project-URL: Repository, https://github.com/mj-hofmann/TAInstCalorimetry
